audyo/__init__.py
audyo/microphone.py
audyo/speaker.py
audyo-1.1.3.dist-info/AUTHORS.rst
audyo-1.1.3.dist-info/LICENSE.txt
audyo-1.1.3.dist-info/METADATA
audyo-1.1.3.dist-info/WHEEL
audyo-1.1.3.dist-info/entry_points.txt
audyo-1.1.3.dist-info/top_level.txt
audyo-1.1.3.dist-info/RECORD
